odoo9_addon_product_pricelist_tax_included-9.0.1.0.0-py2.7-nspkg.pth
odoo9_addon_product_pricelist_tax_included-9.0.1.0.0.dist-info/DESCRIPTION.rst
odoo9_addon_product_pricelist_tax_included-9.0.1.0.0.dist-info/METADATA
odoo9_addon_product_pricelist_tax_included-9.0.1.0.0.dist-info/RECORD
odoo9_addon_product_pricelist_tax_included-9.0.1.0.0.dist-info/WHEEL
odoo9_addon_product_pricelist_tax_included-9.0.1.0.0.dist-info/metadata.json
odoo9_addon_product_pricelist_tax_included-9.0.1.0.0.dist-info/namespace_packages.txt
odoo9_addon_product_pricelist_tax_included-9.0.1.0.0.dist-info/top_level.txt
odoo_addons/product_pricelist_tax_included/README.rst
odoo_addons/product_pricelist_tax_included/__init__.py
odoo_addons/product_pricelist_tax_included/__openerp__.py
odoo_addons/product_pricelist_tax_included/i18n/es.po
odoo_addons/product_pricelist_tax_included/models/__init__.py
odoo_addons/product_pricelist_tax_included/models/product.py
odoo_addons/product_pricelist_tax_included/static/description/icon.png
odoo_addons/product_pricelist_tax_included/tests/__init__.py
odoo_addons/product_pricelist_tax_included/tests/test_product_list_price_tax.py
odoo_addons/product_pricelist_tax_included/views/product_view.xml
